pysistentclass/__init__.py
pysistentclass-0.0.6.dist-info/METADATA
pysistentclass-0.0.6.dist-info/WHEEL
pysistentclass-0.0.6.dist-info/licenses/LICENSE
pysistentclass-0.0.6.dist-info/RECORD
