Metadata-Version: 2.1
Name: pysistentclass
Version: 0.0.6
Summary: A small settings module for python
Project-URL: Homepage, https://github.com/manjaroman2/pysistentclass
Project-URL: Bug Tracker, https://github.com/manjaroman2/pysistentclass/issues
Author-email: manjaroman2 <manjaroman2@protonmail.com>
License-File: LICENSE
Classifier: License :: OSI Approved :: GNU General Public License v3 (GPLv3)
Classifier: Operating System :: OS Independent
Classifier: Programming Language :: Python :: 3
Requires-Python: >=3.11
Requires-Dist: colorlog
Requires-Dist: pyyaml
Requires-Dist: toml
